semitan/__init__.py
tests/__init__.py
tests/test_semitan.py
semitan-0.0.1.dist-info/METADATA
semitan-0.0.1.dist-info/WHEEL
semitan-0.0.1.dist-info/top_level.txt
semitan-0.0.1.dist-info/RECORD
