Metadata-Version: 2.1
Name: semitan
Version: 0.0.1
Summary: Library that interacts with Tan API
Home-page: https://github.com/marcpaulchan/semitan
Author: kikadisa
Author-email: kikadisa@gmail.com
License: MIT
Keywords: tan transport transports metropolitain semitan nantes tram chronobus bus
Platform: UNKNOWN
Classifier: Programming Language :: Python :: 3
Classifier: License :: OSI Approved :: MIT License
Classifier: Operating System :: OS Independent
Requires-Python: >=3.6
Requires-Dist: requests
